pylama2codeclimate.py
pylama2codeclimate-1.3.dist-info/LICENSE
pylama2codeclimate-1.3.dist-info/METADATA
pylama2codeclimate-1.3.dist-info/WHEEL
pylama2codeclimate-1.3.dist-info/entry_points.txt
pylama2codeclimate-1.3.dist-info/top_level.txt
pylama2codeclimate-1.3.dist-info/RECORD
