Metadata-Version: 2.1
Name: pylama2codeclimate
Version: 1.3
Summary: Converts the (parsable) pylama output to codeclimate.json format
Home-page: https://gitlab.com/alelec/pylama2codeclimate
Author: Andrew Leech
Author-email: andrew@alelec.net
License: MIT
License-File: LICENSE
